[
{"key": "chapterno", "value": "5"},
{"key": "mainlink", "value": "/templates/pages/3-user2/4-AboutBook"},
{"key": "prevchapter", "value": "/templates/pages/3-user2/9-Chapter4"},
{"key": "nextchapter", "value": "/templates/pages/3-user2/11-Chapter6"},
{"key": "paragraphs", "value": ["Когда я в ту ночь возвратился в Уэст-Эгг из Нью-Йорка, я было испугался, что у меня в доме пожар. Два часа ночи, а вся оконечность мыса ярко освещена, кусты выступают из мглы, точно призраки, на телеграфных проводах играют длинные блики света. Но такси свернуло за угол, и я увидел, что это вилла Гэтсби сияет всеми огнями от башен до погребов.",

"Сперва я решил, что происходит очередное сборище и разгулявшиеся гости, затеяв игру в прятки или в «море волнуется», распространились по всем этажам. Но уж очень тихо было кругом. Только ветер гудел в проводах, и огни то меркли, то снова вспыхивали, как будто дом подмигивал ночи.", 

"Такси с кряхтением отъехало от моего крыльца, и тут я увидел Гэтсби, который быстро шел по газону, направляясь ко мне."
]}
]